themis.finals.attack.result-1.2.0-py3.5-nspkg.pth
themis/finals/attack/result/__about__.py
themis/finals/attack/result/__init__.py
themis.finals.attack.result-1.2.0.dist-info/DESCRIPTION.rst
themis.finals.attack.result-1.2.0.dist-info/METADATA
themis.finals.attack.result-1.2.0.dist-info/RECORD
themis.finals.attack.result-1.2.0.dist-info/WHEEL
themis.finals.attack.result-1.2.0.dist-info/metadata.json
themis.finals.attack.result-1.2.0.dist-info/namespace_packages.txt
themis.finals.attack.result-1.2.0.dist-info/top_level.txt
