Metadata-Version: 2.0
Name: themis.finals.attack.result
Version: 1.2.0
Summary: Themis Finals attack result constants
Home-page: https://github.com/themis-project/themis-finals-attack-result-py
Author: Alexander Pyatkin
Author-email: aspyatkin@gmail.com
License: MIT
Platform: UNKNOWN
Requires-Dist: setuptools (>=35.0.0)
